trello_to_audit_report/__init__.py
trello_to_audit_report/__version__.py
trello_to_audit_report/finding.py
trello_to_audit_report/finding_list.py
trello_to_audit_report/trello_to_audit_markdown.py
trello_to_audit_report-0.1.3.dist-info/LICENSE
trello_to_audit_report-0.1.3.dist-info/METADATA
trello_to_audit_report-0.1.3.dist-info/WHEEL
trello_to_audit_report-0.1.3.dist-info/entry_points.txt
trello_to_audit_report-0.1.3.dist-info/top_level.txt
trello_to_audit_report-0.1.3.dist-info/RECORD
