Metadata-Version: 2.1
Name: trello-to-audit-report
Version: 0.1.3
Home-page: https://github.com/chainaccelorg/trello_to_audit_report
Author: Cyfrin
License: MIT
Classifier: Development Status :: 2 - Pre-Alpha
Classifier: Intended Audience :: Developers
Classifier: License :: OSI Approved :: MIT License
Classifier: Programming Language :: Python :: 3.7
Classifier: Programming Language :: Python :: 3.8
Classifier: Programming Language :: Python :: 3.9
Classifier: Programming Language :: Python :: 3.10
Requires-Python: >=3.7, <4
License-File: LICENSE
Requires-Dist: certifi
Requires-Dist: charset-normalizer
Requires-Dist: idna
Requires-Dist: requests
Requires-Dist: urllib3
Requires-Dist: python-dotenv
Requires-Dist: pypandoc
Requires-Dist: pytest
